detail/__init__.py
detail/client/__init__.py
detail/client/attrs.py
detail/client/constants.py
detail/client/context.py
detail/client/disable.py
detail/client/instrumentation/__init__.py
detail/client/instrumentation/celery.py
detail/client/instrumentation/dbapi.py
detail/client/instrumentation/ddpsycopg2.py
detail/client/instrumentation/django.py
detail/client/instrumentation/env.py
detail/client/instrumentation/fastapi.py
detail/client/instrumentation/flask.py
detail/client/instrumentation/grpc.py
detail/client/instrumentation/http.py
detail/client/instrumentation/psycopg2.py
detail/client/instrumentation/random.py
detail/client/instrumentation/redis.py
detail/client/instrumentation/sqlalchemy.py
detail/client/instrumentation/sqlite3.py
detail/client/instrumentation/thread.py
detail/client/instrumentation/times.py
detail/client/instrumentation/uuid.py
detail/client/instrumentation/wrappers.py
detail/client/instrumentor.py
detail/client/logs.py
detail/client/models.py
detail/client/otel.py
detail/client/sentry.py
detail/client/serialization.py
detail/client/stack.py
detail_sdk-0.2.1.dist-info/METADATA
detail_sdk-0.2.1.dist-info/WHEEL
detail_sdk-0.2.1.dist-info/RECORD
